drf_ember_backend/__init__.py
drf_ember_backend/exception_handlers.py
drf_ember_backend/parsers.py
drf_ember_backend/renderers.py
drf_ember_backend-1.1.dist-info/DESCRIPTION.rst
drf_ember_backend-1.1.dist-info/METADATA
drf_ember_backend-1.1.dist-info/RECORD
drf_ember_backend-1.1.dist-info/WHEEL
drf_ember_backend-1.1.dist-info/metadata.json
drf_ember_backend-1.1.dist-info/top_level.txt
