Metadata-Version: 2.0
Name: drf-ember-backend
Version: 1.1
Summary: UNKNOWN
Home-page: UNKNOWN
Author: johnbradley
Author-email: UNKNOWN
License: UNKNOWN
Platform: UNKNOWN
Requires-Dist: Django
Requires-Dist: djangorestframework
Requires-Dist: six
